msg91/__init__.py
msg91/services/__init__.py
msg91/services/campaign_service.py
msg91/services/otp_service.py
tests/__init__.py
tests/test_campaign_service.py
tests/test_otp_service.py
prashant_test_package-0.0.1.dist-info/METADATA
prashant_test_package-0.0.1.dist-info/WHEEL
prashant_test_package-0.0.1.dist-info/top_level.txt
prashant_test_package-0.0.1.dist-info/RECORD
